stam_pytorch/__init__.py
stam_pytorch/stam.py
stam_pytorch-0.0.4.dist-info/LICENSE
stam_pytorch-0.0.4.dist-info/METADATA
stam_pytorch-0.0.4.dist-info/WHEEL
stam_pytorch-0.0.4.dist-info/top_level.txt
stam_pytorch-0.0.4.dist-info/RECORD
